mulu_rsgz/__init__.py
mulu_rsgz/file/__init__.py
mulu_rsgz/file/files.py
mulu_rsgz/mulu/__init__.py
mulu_rsgz/mulu/dirs.py
mulu_rsgz/python/__init__.py
mulu_rsgz/python/dabao.py
mulu_rsgz/the_str/__init__.py
mulu_rsgz/the_str/str_mangguo.py
mulu_rsgz-0.0.17.dist-info/METADATA
mulu_rsgz-0.0.17.dist-info/WHEEL
mulu_rsgz-0.0.17.dist-info/licenses/LICENSE
mulu_rsgz-0.0.17.dist-info/RECORD
