Metadata-Version: 2.1
Name: mulu_rsgz
Version: 0.0.17
Summary: 这是 个人 工具库
Project-URL: Homepage, https://github.com/rsgz
Author-email: rsgz <2966261184@qq.com>
License: Copyright (c) 2022 The Python Packaging Authority
License-File: LICENSE
Classifier: License :: OSI Approved :: MIT License
Classifier: Operating System :: OS Independent
Classifier: Programming Language :: Python :: 3
Requires-Python: >=3.7
Requires-Dist: numpy>=1.21.6
